sendsms_pkg/__init__.py
sendsms_pkg/sns.py
x20157576_sns_pkg-0.0.1.dist-info/LICENSE
x20157576_sns_pkg-0.0.1.dist-info/METADATA
x20157576_sns_pkg-0.0.1.dist-info/WHEEL
x20157576_sns_pkg-0.0.1.dist-info/top_level.txt
x20157576_sns_pkg-0.0.1.dist-info/RECORD
