Metadata-Version: 2.1
Name: x20157576-sns-pkg
Version: 0.0.1
Summary: A small boto3 send SNS text message
Home-page: https://github.com/x20157576/cpp_ca
Author: x20157576
Author-email: x20157576@student.ncirl.ie
License: UNKNOWN
Platform: UNKNOWN
Classifier: Programming Language :: Python :: 3
Classifier: License :: OSI Approved :: MIT License
Classifier: Operating System :: OS Independent
Requires-Python: >=3.6
Requires-Dist: boto3
